[
 {
  "default_cost_center": null, 
  "default_expense_account": null, 
  "default_income_account": null, 
  "description": null, 
  "docstatus": 0, 
  "doctype": "Item Group", 
  "is_group": 0, 
  "item_group_name": "All Item Groups", 
  "lft": 1, 
  "modified": "2016-04-23 00:50:29.703140", 
  "name": "All Item Groups", 
  "old_parent": "",
  "parent_item_group": "",
  "rgt": 14, 
  "route": "all-item-groups", 
  "show_in_website": 0, 
  "slideshow": null, 
  "website_specifications": []
 }, 
 {
  "default_cost_center": null, 
  "default_expense_account": null, 
  "default_income_account": null, 
  "description": null, 
  "docstatus": 0, 
  "doctype": "Item Group", 
  "is_group": 0, 
  "item_group_name": "Products", 
  "lft": 2, 
  "modified": "2016-03-17 10:33:12.894029", 
  "name": "Products", 
  "old_parent": "All Item Groups", 
  "parent_item_group": "All Item Groups", 
  "rgt": 3, 
  "route": "all-item-groups/products", 
  "show_in_website": 1, 
  "slideshow": null, 
  "website_specifications": []
 }, 
 {
  "default_cost_center": null, 
  "default_expense_account": null, 
  "default_income_account": null, 
  "description": null, 
  "docstatus": 0, 
  "doctype": "Item Group", 
  "is_group": 0, 
  "item_group_name": "Raw Material", 
  "lft": 4, 
  "modified": "2016-03-17 10:33:12.940846", 
  "name": "Raw Material", 
  "old_parent": "All Item Groups", 
  "parent_item_group": "All Item Groups", 
  "rgt": 5, 
  "route": "all-item-groups/raw-material", 
  "show_in_website": 0, 
  "slideshow": null, 
  "website_specifications": []
 }, 
 {
  "default_cost_center": null, 
  "default_expense_account": null, 
  "default_income_account": null, 
  "description": null, 
  "docstatus": 0, 
  "doctype": "Item Group", 
  "is_group": 0, 
  "item_group_name": "Services", 
  "lft": 6, 
  "modified": "2016-03-17 10:33:12.949074", 
  "name": "Services", 
  "old_parent": "All Item Groups", 
  "parent_item_group": "All Item Groups", 
  "rgt": 7, 
  "route": "all-item-groups/services", 
  "show_in_website": 0, 
  "slideshow": null, 
  "website_specifications": []
 }, 
 {
  "default_cost_center": null, 
  "default_expense_account": null, 
  "default_income_account": null, 
  "description": null, 
  "docstatus": 0, 
  "doctype": "Item Group", 
  "is_group": 0, 
  "item_group_name": "Sub Assemblies", 
  "lft": 8, 
  "modified": "2016-03-17 10:33:12.966834", 
  "name": "Sub Assemblies", 
  "old_parent": "All Item Groups", 
  "parent_item_group": "All Item Groups", 
  "rgt": 9, 
  "route": "all-item-groups/sub-assemblies", 
  "show_in_website": 0, 
  "slideshow": null, 
  "website_specifications": []
 }, 
 {
  "default_cost_center": null, 
  "default_expense_account": null, 
  "default_income_account": null, 
  "description": null, 
  "docstatus": 0, 
  "doctype": "Item Group", 
  "is_group": 0, 
  "item_group_name": "Consumable", 
  "lft": 10, 
  "modified": "2016-03-17 10:33:12.978048", 
  "name": "Consumable", 
  "old_parent": "All Item Groups", 
  "parent_item_group": "All Item Groups", 
  "rgt": 11, 
  "route": "all-item-groups/consumable", 
  "show_in_website": 0, 
  "slideshow": null, 
  "website_specifications": []
 }, 
 {
  "default_cost_center": null, 
  "default_expense_account": null, 
  "default_income_account": null, 
  "description": null, 
  "docstatus": 0, 
  "doctype": "Item Group", 
  "is_group": 0, 
  "item_group_name": "Property Charge", 
  "lft": 12, 
  "modified": "2016-04-23 00:50:29.704139", 
  "name": "Property Charge", 
  "old_parent": "All Item Groups", 
  "parent_item_group": "All Item Groups", 
  "rgt": 13, 
  "route": "all-item-groups/property-charge", 
  "show_in_website": 0, 
  "slideshow": null, 
  "website_specifications": []
 }
]